app_store_web_scraper/__about__.py
app_store_web_scraper/__init__.py
app_store_web_scraper/_entry.py
app_store_web_scraper/_errors.py
app_store_web_scraper/_session.py
app_store_web_scraper/_utils.py
app_store_web_scraper-0.1.1.dist-info/METADATA
app_store_web_scraper-0.1.1.dist-info/WHEEL
app_store_web_scraper-0.1.1.dist-info/licenses/LICENCE
app_store_web_scraper-0.1.1.dist-info/RECORD
