Metadata-Version: 2.3
Name: app-store-web-scraper
Version: 0.1.1
Summary: Scrape reviews from Apple's App Store
Project-URL: Homepage, https://github.com/futurice/app-store-web-scraper
Project-URL: Source, https://github.com/futurice/app-store-web-scraper
Author: Denis Washington, Eric Lim
License-Expression: MIT
License-File: LICENCE
Keywords: app store,ios,ios apps,podcasts,review,scraper,scraping
Classifier: Intended Audience :: Developers
Classifier: License :: OSI Approved :: MIT License
Classifier: Operating System :: OS Independent
Classifier: Programming Language :: Python :: 3
Classifier: Programming Language :: Python :: 3.8
Classifier: Programming Language :: Python :: 3.9
Classifier: Programming Language :: Python :: 3.10
Classifier: Programming Language :: Python :: 3.11
Classifier: Programming Language :: Python :: 3.12
Classifier: Topic :: Internet :: WWW/HTTP
Classifier: Topic :: Scientific/Engineering :: Information Analysis
Classifier: Typing :: Typed
Requires-Python: >=3.8
Requires-Dist: urllib3<3,>=2.0.0
